apidance/__init__.py
apidance/client.py
apidance/exceptions.py
apidance/models.py
apidance/utils/__init__.py
apidance/utils/markdown.py
apidance-0.7.1.dist-info/licenses/LICENSE
apidance-0.7.1.dist-info/METADATA
apidance-0.7.1.dist-info/WHEEL
apidance-0.7.1.dist-info/top_level.txt
apidance-0.7.1.dist-info/RECORD
