Metadata-Version: 2.4
Name: apidance
Version: 0.7.1
Summary: https://apidance.pro/ community python sdk
Author-email: script-money <hello@script.money>
License: MIT
Requires-Python: >=3.10
License-File: LICENSE
Requires-Dist: httpx>=0.25.2
Requires-Dist: mcp[cli]>=1.3.0
Requires-Dist: python-dotenv>=1.0.0
Requires-Dist: pydantic>=2.0.0
Dynamic: license-file
